{"4 Stroke": "https://www.caradisiac.com/auto--4-stroke/", "Abarth": "https://www.caradisiac.com/auto--abarth/", "Ac": "https://www.caradisiac.com/auto--ac/", "Acrea": "https://www.caradisiac.com/auto--acrea/", "Acura": "https://www.caradisiac.com/auto--acura/", "Ad Tramontana": "https://www.caradisiac.com/auto--ad-tramontana/", "Adler": "https://www.caradisiac.com/auto--adler/modeles/", "Aiways": "https://www.caradisiac.com/auto--aiways/", "Aixam": "https://www.caradisiac.com/auto--aixam/", "Al Melling": "https://www.caradisiac.com/auto--al-melling/", "Aleko": "https://www.caradisiac.com/auto--aleko/modeles/", "Alfa Romeo": "https://www.caradisiac.com/auto--alfa-romeo/", "Alke": "https://www.caradisiac.com/auto--alke/modeles/", "Alpina": "https://www.caradisiac.com/auto--alpina/", "Alpine": "https://www.caradisiac.com/auto--alpine-renault/", "Alvis": "https://www.caradisiac.com/auto--alvis/", "Am General": "https://www.caradisiac.com/auto--am-general/modeles/", "Amc": "https://www.caradisiac.com/auto--amc/", "Amphicar": "https://www.caradisiac.com/auto--amphicar/", "Anaig": "https://www.caradisiac.com/auto--anaig/modeles/", "Apal": "https://www.caradisiac.com/auto--apal/modeles/", "Aptera Motors": "https://www.caradisiac.com/auto--aptera-motors/", "Ariel": "https://www.caradisiac.com/auto--ariel/", "Armstrong Siddeley": "https://www.caradisiac.com/auto--armstrong-siddeley/", "Aro": "https://www.caradisiac.com/auto--aro/modeles/", "Artega": "https://www.caradisiac.com/auto--artega/", "Ascari": "https://www.caradisiac.com/auto--ascari/", "Aspark": "https://www.caradisiac.com/auto--aspark/", "Aston Martin": "https://www.caradisiac.com/auto--aston-martin/", "Auburn": "https://www.caradisiac.com/auto--auburn/modeles/", "Audi": "https://www.caradisiac.com/auto--audi/", "Austin": "https://www.caradisiac.com/auto--austin/", "Austin Healey": "https://www.caradisiac.com/auto--austin-healey/", "Auto Union": "https://www.caradisiac.com/auto--auto-union/", "Autobianchi": "https://www.caradisiac.com/auto--autobianchi/", "Auverland": "https://www.caradisiac.com/auto--auverland/", "Bee Automobiles": "https://www.caradisiac.com/auto--bee-automobiles/", "Beijing": "https://www.caradisiac.com/auto--beijing/", "Bellier": "https://www.caradisiac.com/auto--bellier/modeles/", "Bentley": "https://www.caradisiac.com/auto--bentley/", "Berliet": "https://www.caradisiac.com/auto--berliet/", "Bertone": "https://www.caradisiac.com/auto--bertone/", "Bitter": "https://www.caradisiac.com/auto--bitter/", "Bizzarrini": "https://www.caradisiac.com/auto--bizzarrini/", "Bluecar Groupe Bollore": "https://www.caradisiac.com/auto--bluecar-groupe-bollore/modeles/", "Bmw": "https://www.caradisiac.com/auto--bmw/", "Bollore": "https://www.caradisiac.com/auto--bollore/", "Bongarini": "https://www.caradisiac.com/auto--bongarini/", "Booxt": "https://www.caradisiac.com/auto--booxt/modeles/", "Borgward": "https://www.caradisiac.com/auto--borgward/", "Bowler": "https://www.caradisiac.com/auto--bowler/", "Brabus": "https://www.caradisiac.com/auto--brabus/", "Bremach": "https://www.caradisiac.com/auto--bremach/modeles/", "Brilliance": "https://www.caradisiac.com/auto--brilliance/", "Bristol": "https://www.caradisiac.com/auto--bristol/", "Brooke Cars": "https://www.caradisiac.com/auto--brooke-cars/", "Bugatti": "https://www.caradisiac.com/auto--bugatti/", "Buick": "https://www.caradisiac.com/auto--buick/", "Burby S": "https://www.caradisiac.com/auto--burby-s/modeles/", "Byd": "https://www.caradisiac.com/auto--byd/", "Cadillac": "https://www.caradisiac.com/auto--cadillac/", "Caparo": "https://www.caradisiac.com/auto--caparo/", "Carbodies": "https://www.caradisiac.com/auto--carbodies/modeles/", "Carbontech": "https://www.caradisiac.com/auto--carbontech/", "Carver": "https://www.caradisiac.com/auto--carver/", "Casalini": "https://www.caradisiac.com/auto--casalini/avis/", "Caterham": "https://www.caradisiac.com/auto--caterham/", "Cg": "https://www.caradisiac.com/auto--cg/", "Chatenet": "https://www.caradisiac.com/auto--chatenet/", "Chenard Et Walcker": "https://www.caradisiac.com/auto--chenard-et-walcker/modeles/", "Chery": "https://www.caradisiac.com/auto--chery/", "Chevrolet": "https://www.caradisiac.com/auto--chevrolet/", "China Automobile": "https://www.caradisiac.com/auto--china-automobile/", "Chrysler": "https://www.caradisiac.com/auto--chrysler/", "Citroen": "https://www.caradisiac.com/auto--citroen/", "Clenet": "https://www.caradisiac.com/auto--clenet/avis/", "Commuter Cars": "https://www.caradisiac.com/auto--commuter-cars/", "Connaught": "https://www.caradisiac.com/auto--connaught/", "Coste": "https://www.caradisiac.com/auto--coste/modeles/", "Courb": "https://www.caradisiac.com/auto--courb/modeles/", "Cupra": "https://www.caradisiac.com/auto--cupra/", "Curbee": "https://www.caradisiac.com/auto--curbee/modeles/", "Dacia": "https://www.caradisiac.com/auto--dacia/", "Daewoo": "https://www.caradisiac.com/auto--daewoo/", "Daf": "https://www.caradisiac.com/auto--daf/", "Daihatsu": "https://www.caradisiac.com/auto--daihatsu/", "Daimler": "https://www.caradisiac.com/auto--daimler/", "Dallara": "https://www.caradisiac.com/auto--dallara/", "Dangel": "https://www.caradisiac.com/auto--dangel/", "Darmont": "https://www.caradisiac.com/auto--darmont/modeles/", "Datsun": "https://www.caradisiac.com/auto--datsun/", "De Fremond": "https://www.caradisiac.com/auto--de-fremond/modeles/", "De La Chapelle": "https://www.caradisiac.com/auto--de-la-chapelle/", "De Lorean": "https://www.caradisiac.com/auto--de-lorean/", "De Soto": "https://www.caradisiac.com/auto--de-soto/modeles/", "De Tomaso": "https://www.caradisiac.com/auto--de-tomaso/", "Delage": "https://www.caradisiac.com/auto--delage/", "Delahaye": "https://www.caradisiac.com/auto--delahaye/", "Denza": "https://www.caradisiac.com/auto--denza/", "Deronda": "https://www.caradisiac.com/auto--deronda/", "Deutsch-bonnet": "https://www.caradisiac.com/auto--deutsch-bonnet/modeles/", "Devinci": "https://www.caradisiac.com/auto--devinci/modeles/", "Devon": "https://www.caradisiac.com/auto--devon/", "Dfsk": "https://www.caradisiac.com/auto--dfsk/modeles/", "Dkw": "https://www.caradisiac.com/auto--dkw/", "Dodge": "https://www.caradisiac.com/auto--dodge/", "Dongfeng": "https://www.caradisiac.com/auto--dongfeng/", "Donkervoort": "https://www.caradisiac.com/auto--donkervoort/", "Donnet": "https://www.caradisiac.com/auto--donnet/modeles/", "Dr Motor": "https://www.caradisiac.com/auto--dr-motor/", "Ds": "https://www.caradisiac.com/auto--ds/", "Due": "https://www.caradisiac.com/auto--due/modeles/", "Duesenberg": "https://www.caradisiac.com/auto--duesenberg/", "Eagle": "https://www.caradisiac.com/auto--eagle/modeles/", "Ebro": "https://www.caradisiac.com/auto--ebro/modeles/", "Edsel": "https://www.caradisiac.com/auto--edsel/", "Elv": "https://www.caradisiac.com/auto--elv/avis/", "Embuggy": "https://www.caradisiac.com/auto--embuggy/modeles/", "Erad": "https://www.caradisiac.com/auto--erad/modeles/", "Estrima": "https://www.caradisiac.com/auto--estrima/modeles/", "Exagon Motors": "https://www.caradisiac.com/auto--exagon-motors/", "Excalibur": "https://www.caradisiac.com/auto--excalibur/avis/", "Facel Vega": "https://www.caradisiac.com/auto--facel-vega/", "Fam Automobiles": "https://www.caradisiac.com/auto--fam-automobiles/", "Faraday Future": "https://www.caradisiac.com/auto--faraday-future/", "Faralli & Mazzanti": "https://www.caradisiac.com/auto--faralli-mazzanti/", "Farbio": "https://www.caradisiac.com/auto--farbio/", "Ferrari": "https://www.caradisiac.com/auto--ferrari/", "Fest": "https://www.caradisiac.com/auto--fest/modeles/", "Fiat": "https://www.caradisiac.com/auto--fiat/", "Fioravanti": "https://www.caradisiac.com/auto--fioravanti/", "Fisker": "https://www.caradisiac.com/auto--fisker/", "Ford": "https://www.caradisiac.com/auto--ford/", "Fornasari": "https://www.caradisiac.com/auto--fornasari/", "Foton": "https://www.caradisiac.com/marque-moto--foton/modeles/", "Fso": "https://www.caradisiac.com/auto--fso/", "Gac Gonow": "https://www.caradisiac.com/auto--gac-gonow/modeles/", "Gac Motor": "https://www.caradisiac.com/auto--gac-motor/", "Geely": "https://www.caradisiac.com/auto--geely/", "Genesis": "https://www.caradisiac.com/auto--genesis/", "Gillet": "https://www.caradisiac.com/auto--gillet/", "Ginetta": "https://www.caradisiac.com/auto--ginetta/", "Giotti Victoria": "https://www.caradisiac.com/marque-moto--giotti-victoria/modeles/", "Glas": "https://www.caradisiac.com/auto--glas/", "Gmc": "https://www.caradisiac.com/auto--gmc/", "Gme": "https://www.caradisiac.com/auto--gme/", "Goupil": "https://www.caradisiac.com/auto--goupil/modeles/", "Grandin": "https://www.caradisiac.com/auto--grandin/modeles/", "Great Wall": "https://www.caradisiac.com/auto--great-wall/", "Grecav": "https://www.caradisiac.com/auto--grecav/modeles/", "Gumpert": "https://www.caradisiac.com/auto--gumpert/", "Healey": "https://www.caradisiac.com/auto--healey/", "Helem": "https://www.caradisiac.com/auto--helem/", "Hennessey": "https://www.caradisiac.com/auto--hennessey/", "Heuliez": "https://www.caradisiac.com/auto--heuliez/", "Hillman": "https://www.caradisiac.com/auto--hillman/modeles/", "Hispano Suiza Cars": "https://www.caradisiac.com/auto--hispano-suiza-cars/", "Holden": "https://www.caradisiac.com/auto--holden/", "Hommell": "https://www.caradisiac.com/auto--hommell/", "Honda": "https://www.caradisiac.com/auto--honda/", "Hongqi": "https://www.caradisiac.com/marque-moto--hongqi/", "Hopium": "https://www.caradisiac.com/auto--hopium/", "Hotchkiss": "https://www.caradisiac.com/auto--hotchkiss/", "Howmet": "https://www.caradisiac.com/auto--howmet/", "Hudson": "https://www.caradisiac.com/auto--hudson/modeles/", "Humber": "https://www.caradisiac.com/auto--humber/modeles/", "Hummer": "https://www.caradisiac.com/auto--hummer/", "Hyundai": "https://www.caradisiac.com/auto--hyundai/", "Imperial": "https://www.caradisiac.com/auto--imperial/", "Ineos": "https://www.caradisiac.com/auto--ineos/", "Infiniti": "https://www.caradisiac.com/auto--infiniti/", "Innocenti": "https://www.caradisiac.com/auto--innocenti/", "Innotech": "https://www.caradisiac.com/auto--innotech/", "Intermeccanica": "https://www.caradisiac.com/auto--intermeccanica/modeles/", "International": "https://www.caradisiac.com/auto--international/modeles/", "Invicta": "https://www.caradisiac.com/auto--invicta/", "Iso": "https://www.caradisiac.com/auto--iso/", "Isorivolta": "https://www.caradisiac.com/auto--isorivolta/", "Isuzu": "https://www.caradisiac.com/auto--isuzu/", "Italcar": "https://www.caradisiac.com/auto--italcar/modeles/", "Iveco": "https://www.caradisiac.com/auto--iveco/", "Jaguar": "https://www.caradisiac.com/auto--jaguar/", "Jannarelly": "https://www.caradisiac.com/marque-moto--jannarelly/modeles/", "Jdm Simpa": "https://www.caradisiac.com/auto--jdm-simpa/", "Jeep": "https://www.caradisiac.com/auto--jeep/", "Jensen": "https://www.caradisiac.com/auto--jensen/", "Jiayuan": "https://www.caradisiac.com/auto--jiayuan/modeles/", "Karma": "https://www.caradisiac.com/auto--karma/", "Kassbohrer Setra": "https://www.caradisiac.com/auto--kassbohrer-setra/modeles/", "Kia": "https://www.caradisiac.com/auto--kia/", "Koenigsegg": "https://www.caradisiac.com/auto--koenigsegg/", "Ktm": "https://www.caradisiac.com/auto--ktm/", "Lada": "https://www.caradisiac.com/auto--lada/", "Lagonda": "https://www.caradisiac.com/auto--lagonda/", "Lamborghini": "https://www.caradisiac.com/auto--lamborghini/", "Lancia": "https://www.caradisiac.com/auto--lancia/", "Land Rover": "https://www.caradisiac.com/auto--land-rover/", "Landwind": "https://www.caradisiac.com/auto--landwind/", "Lantana": "https://www.caradisiac.com/auto--lantana/avis/", "Laraki": "https://www.caradisiac.com/auto--laraki/", "Ldv": "https://www.caradisiac.com/auto--ldv/", "Leapmotor": "https://www.caradisiac.com/auto--leapmotor/", "Levc": "https://www.caradisiac.com/auto--levc/modeles/", "Lexus": "https://www.caradisiac.com/auto--lexus/", "Lightyear": "https://www.caradisiac.com/auto--lightyear/", "Ligier": "https://www.caradisiac.com/auto--ligier/", "Lincoln": "https://www.caradisiac.com/auto--lincoln/", "Lister": "https://www.caradisiac.com/auto--lister/", "Little": "https://www.caradisiac.com/auto--little/", "Lola": "https://www.caradisiac.com/auto--lola/", "London Taxi Company": "https://www.caradisiac.com/auto--london-taxi-company/modeles/", "Loremo": "https://www.caradisiac.com/auto--loremo/", "Lotus": "https://www.caradisiac.com/auto--lotus/", "Lucid": "https://www.caradisiac.com/auto--lucid/", "Lumeneo": "https://www.caradisiac.com/auto--lumeneo/", "Lynk & Co": "https://www.caradisiac.com/auto--lynk-co/", "Mahindra": "https://www.caradisiac.com/auto--mahindra/", "Man": "https://www.caradisiac.com/auto--man/", "Marcadier": "https://www.caradisiac.com/auto--marcadier/modeles/", "Marcos": "https://www.caradisiac.com/auto--marcos/", "Martin": "https://www.caradisiac.com/auto--martin/avis/", "Marussia": "https://www.caradisiac.com/auto--marussia/", "Maruti": "https://www.caradisiac.com/auto--maruti/", "Maserati": "https://www.caradisiac.com/auto--maserati/", "Matra": "https://www.caradisiac.com/auto--matra/", "Maxus": "https://www.caradisiac.com/auto--maxus/", "Maybach": "https://www.caradisiac.com/auto--maybach/", "Mazda": "https://www.caradisiac.com/auto--mazda/", "Mclaren": "https://www.caradisiac.com/auto--mclaren/", "Mdi": "https://www.caradisiac.com/auto--mdi/", "Mega": "https://www.caradisiac.com/auto--mega/", "Melkus": "https://www.caradisiac.com/auto--melkus/", "Mercedes": "https://www.caradisiac.com/auto--mercedes/", "Mercedes-amg": "https://www.caradisiac.com/auto--mercedes-amg/", "Mercury": "https://www.caradisiac.com/auto--mercury/", "Messerschmitt": "https://www.caradisiac.com/auto--messerschmitt/modeles/", "Mev": "https://www.caradisiac.com/auto--mev/modeles/", "Meyers Manx": "https://www.caradisiac.com/auto--meyers-manx/modeles/", "Mg": "https://www.caradisiac.com/auto--mg/", "Mia Electric": "https://www.caradisiac.com/auto--mia-electric/", "Micro": "https://www.caradisiac.com/auto--micro/", "Microcar": "https://www.caradisiac.com/auto--microcar/", "Microdrive": "https://www.caradisiac.com/auto--microdrive/modeles/", "Minauto": "https://www.caradisiac.com/auto--minauto/modeles/", "Mini": "https://www.caradisiac.com/auto--mini/", "Mitsubishi": "https://www.caradisiac.com/auto--mitsubishi/", "Mitsubishi Fuso": "https://www.caradisiac.com/auto--mitsubishi-fuso/", "Mitsuoka": "https://www.caradisiac.com/auto--mitsuoka/", "Mlt": "https://www.caradisiac.com/auto--mlt/modeles/", "Mobilize": "https://www.caradisiac.com/auto--mobilize/", "Moke": "https://www.caradisiac.com/auto--moke/", "Monteverdi": "https://www.caradisiac.com/auto--monteverdi/modeles/", "Morgan": "https://www.caradisiac.com/auto--morgan/", "Morris": "https://www.caradisiac.com/auto--morris/", "Mosler": "https://www.caradisiac.com/auto--mosler/", "Mpm Motors": "https://www.caradisiac.com/auto--mpm-motors/", "Munro": "https://www.caradisiac.com/auto--munro/modeles/", "Mvs": "https://www.caradisiac.com/auto--mvs/modeles/", "Mygale": "https://www.caradisiac.com/auto--mygale/", "Namx": "https://www.caradisiac.com/auto--namx/", "Nanjing": "https://www.caradisiac.com/auto--nanjing/", "Nash": "https://www.caradisiac.com/auto--nash/modeles/", "Neckar": "https://www.caradisiac.com/auto--neckar/", "Newteon": "https://www.caradisiac.com/auto--newteon/", "Newyark": "https://www.caradisiac.com/auto--newyark/modeles/", "Nio": "https://www.caradisiac.com/auto--nio/", "Nissan": "https://www.caradisiac.com/auto--nissan/", "Noble": "https://www.caradisiac.com/auto--noble/", "Nosmoke": "https://www.caradisiac.com/auto--nosmoke/modeles/", "Noun Electric": "https://www.caradisiac.com/auto--noun-electric/modeles/", "Nsu": "https://www.caradisiac.com/auto--nsu/", "Numexia": "https://www.caradisiac.com/auto--numexia/", "Oldsmobile": "https://www.caradisiac.com/auto--oldsmobile/", "Opel": "https://www.caradisiac.com/auto--opel/", "Ora": "https://www.caradisiac.com/auto--ora/", "Osi": "https://www.caradisiac.com/auto--osi/modeles/", "Packard": "https://www.caradisiac.com/auto--packard/", "Pagani": "https://www.caradisiac.com/auto--pagani/", "Panhard": "https://www.caradisiac.com/auto--panhard/", "Panoz": "https://www.caradisiac.com/auto--panoz/", "Panther": "https://www.caradisiac.com/auto--panther/photo/", "Pegaso": "https://www.caradisiac.com/auto--pegaso/", "Perana": "https://www.caradisiac.com/auto--perana/", "Peugeot": "https://www.caradisiac.com/auto--peugeot/", "Pgo": "https://www.caradisiac.com/auto--pgo/", "Piaggio": "https://www.caradisiac.com/auto--piaggio/", "Pilbeam": "https://www.caradisiac.com/auto--pilbeam/", "Pininfarina": "https://www.caradisiac.com/auto--pininfarina/", "Plymouth": "https://www.caradisiac.com/auto--plymouth/", "Polestar": "https://www.caradisiac.com/auto--polestar/", "Polski": "https://www.caradisiac.com/auto--polski/", "Pontiac": "https://www.caradisiac.com/auto--pontiac/", "Porsche": "https://www.caradisiac.com/auto--porsche/", "Proton": "https://www.caradisiac.com/auto--proton/", "Protoscar": "https://www.caradisiac.com/auto--protoscar/", "Qoros": "https://www.caradisiac.com/auto--qoros/", "Quant": "https://www.caradisiac.com/auto--quant/", "Radical": "https://www.caradisiac.com/auto--radical/", "Ram": "https://www.caradisiac.com/auto--ram/", "Rcb": "https://www.caradisiac.com/auto--rcb/modeles/", "Realm": "https://www.caradisiac.com/auto--realm/modeles/", "Reliant": "https://www.caradisiac.com/auto--reliant/", "Renault": "https://www.caradisiac.com/auto--renault/", "Renault Trucks": "https://www.caradisiac.com/auto--renault-trucks/", "Rene Bonnet": "https://www.caradisiac.com/auto--rene-bonnet/", "Reva": "https://www.caradisiac.com/auto--reva/", "Reynard": "https://www.caradisiac.com/auto--reynard/", "Riley": "https://www.caradisiac.com/auto--riley/", "Rimac": "https://www.caradisiac.com/auto--rimac/", "Rinspeed": "https://www.caradisiac.com/auto--rinspeed/", "Rivian": "https://www.caradisiac.com/auto--rivian/", "Rolls Royce": "https://www.caradisiac.com/auto--rolls-royce/", "Ronart": "https://www.caradisiac.com/auto--ronart/", "Rosengart": "https://www.caradisiac.com/auto--rosengart/modeles/", "Rover": "https://www.caradisiac.com/auto--rover/", "Russo-baltique": "https://www.caradisiac.com/auto--russo-baltique/", "Saab": "https://www.caradisiac.com/auto--saab/", "Saic": "https://www.caradisiac.com/auto--saic/", "Saleen": "https://www.caradisiac.com/auto--saleen/", "Salica": "https://www.caradisiac.com/auto--salica/", "Salmson": "https://www.caradisiac.com/auto--salmson/", "Samsung": "https://www.caradisiac.com/auto--samsung/", "Santana": "https://www.caradisiac.com/auto--santana/", "Saturn": "https://www.caradisiac.com/auto--saturn/", "Savel": "https://www.caradisiac.com/auto--savel/modeles/", "Saviem": "https://www.caradisiac.com/auto--saviem/", "Sbarro": "https://www.caradisiac.com/auto--sbarro/", "Scania": "https://www.caradisiac.com/auto--scania/", "Scion": "https://www.caradisiac.com/auto--scion/", "Seat": "https://www.caradisiac.com/auto--seat/", "Secma": "https://www.caradisiac.com/auto--secma/", "Seres": "https://www.caradisiac.com/auto--seres/", "Shelby": "https://www.caradisiac.com/auto--shelby/", "Shuanghuan": "https://www.caradisiac.com/auto--shuanghuan/", "Simca": "https://www.caradisiac.com/auto--simca/", "Singer": "https://www.caradisiac.com/auto--singer/", "Sivax": "https://www.caradisiac.com/auto--sivax/", "Skoda": "https://www.caradisiac.com/auto--skoda/", "Skyworth": "https://www.caradisiac.com/auto--skyworth/", "Smart": "https://www.caradisiac.com/auto--smart/", "Sms": "https://www.caradisiac.com/auto--sms/modeles/", "Sovamag": "https://www.caradisiac.com/auto--sovamag/modeles/", "Spectre": "https://www.caradisiac.com/auto--spectre/modeles/", "Spyker": "https://www.caradisiac.com/auto--spyker/", "Srt": "https://www.caradisiac.com/auto--srt/", "Ssangyong": "https://www.caradisiac.com/auto--ssangyong/", "Ssc": "https://www.caradisiac.com/auto--ssc/", "Studebaker": "https://www.caradisiac.com/auto--studebaker/", "Stutz": "https://www.caradisiac.com/auto--stutz/modeles/", "Subaru": "https://www.caradisiac.com/auto--subaru/", "Sunbeam": "https://www.caradisiac.com/auto--sunbeam/", "Suzuki": "https://www.caradisiac.com/auto--suzuki/", "Talbot": "https://www.caradisiac.com/auto--talbot/", "Talbot Simca": "https://www.caradisiac.com/auto--talbot-simca/", "Tata": "https://www.caradisiac.com/auto--tata/", "Teilhol": "https://www.caradisiac.com/auto--teilhol/", "Tesla": "https://www.caradisiac.com/auto--tesla/", "Think": "https://www.caradisiac.com/auto--think/", "Toyota": "https://www.caradisiac.com/auto--toyota/", "Trabant": "https://www.caradisiac.com/auto--trabant/", "Triumph": "https://www.caradisiac.com/auto--triumph/", "Tvr": "https://www.caradisiac.com/auto--tvr/", "Ultima": "https://www.caradisiac.com/auto--ultima/", "Umm": "https://www.caradisiac.com/auto--umm/avis/", "Vaillante": "https://www.caradisiac.com/auto--vaillante/", "Van Hool": "https://www.caradisiac.com/auto--van-hool/modeles/", "Vanden Plas": "https://www.caradisiac.com/auto--vanden-plass/modeles/", "Vauxhall": "https://www.caradisiac.com/auto--vauxhall/", "Velam": "https://www.caradisiac.com/auto--velam/modeles/", "Venturi": "https://www.caradisiac.com/auto--venturi/", "Veritas": "https://www.caradisiac.com/auto--veritas/", "Vespa": "https://www.caradisiac.com/auto--vespa/modeles/", "Vinfast": "https://www.caradisiac.com/auto--vinfast/", "Virago": "https://www.caradisiac.com/auto--virago/", "Volkswagen": "https://www.caradisiac.com/auto--volkswagen/", "Volteis": "https://www.caradisiac.com/auto--volteis/", "Volvo": "https://www.caradisiac.com/auto--volvo/", "Volvo Trucks": "https://www.caradisiac.com/auto--volvo-trucks/", "Wallys Car": "https://www.caradisiac.com/auto--wallys-car/avis/", "Westfield": "https://www.caradisiac.com/auto--westfield/", "Wiesmann": "https://www.caradisiac.com/auto--wiesmann/", "Willys": "https://www.caradisiac.com/auto--willys/", "Wolseley": "https://www.caradisiac.com/auto--wolseley/modeles/", "Xev": "https://www.caradisiac.com/auto--xev/modeles/", "Xiaomi": "https://www.caradisiac.com/auto--xiaomi/", "Xinyang": "https://www.caradisiac.com/auto--xinyang/modeles/", "Xpeng": "https://www.caradisiac.com/auto--xpeng/", "Yangwang": "https://www.caradisiac.com/auto--yangwang/", "Zagato": "https://www.caradisiac.com/auto--zagato/", "Zap": "https://www.caradisiac.com/auto--zap/", "Zastava": "https://www.caradisiac.com/auto--zastava/", "Zeekr": "https://www.caradisiac.com/auto--zeekr/", "Zenn": "https://www.caradisiac.com/auto--zenn/", "Zenvo": "https://www.caradisiac.com/auto--zenvo/"}